lfinancial/__init__.py
lfinancial/factory.py
lfinancial/financial.py
lfinancial/generators/__init__.py
lfinancial/generators/bank.py
lfinancial/generators/card.py
lfinancial/generators/const.py
lfinancial/generators/contry.py
lfinancial/generators/currency.py
lfinancial/generators/document.py
lfinancial/generators/gender.py
lfinancial/generators/industry.py
lfinancial/generators/locale.py
lfinancial/generators/mail.py
lfinancial/generators/name.py
lfinancial/generators/phone.py
lfinancial/generators/stock.py
lfinancial/generators/swift.py
lfinancial/generators/timezone.py
lfinancial-0.3.1.dist-info/LICENSE.txt
lfinancial-0.3.1.dist-info/METADATA
lfinancial-0.3.1.dist-info/WHEEL
lfinancial-0.3.1.dist-info/top_level.txt
lfinancial-0.3.1.dist-info/RECORD
