Metadata-Version: 2.1
Name: lfinancial
Version: 0.3.1
Summary: Generate financial test data
Author: zaneliu
Author-email: lzy291980138@163.com
Classifier: Programming Language :: Python :: 3
Classifier: License :: OSI Approved :: GNU General Public License v2 (GPLv2)
Classifier: Operating System :: OS Independent
License-File: LICENSE.txt
